[{"date": "08-06-2023", "aisle_name": "Peixes", "product_name": "Fil\u00e9 de merluza congelado", "brand": "Costa Sul", "price": 29.98, "package": "500g", "store_name": "Hippo", "store_city": "FLN", "search_term": "Fil\u00e9 de Merluza"}, {"date": "08-06-2023", "aisle_name": "Peixes", "product_name": "Fil\u00e9 de merluza congelado", "brand": "Copacol", "price": 74.99, "package": "800g", "store_name": "BIG by Carrefour", "store_city": "FLN", "search_term": "Fil\u00e9 de Merluza"}, {"date": "08-06-2023", "aisle_name": "Peixes", "product_name": "Fil\u00e9 de merluza congelado", "brand": "Copacol", "price": 74.99, "package": "800g", "store_name": "Carrefour Hiper", "store_city": "FLN", "search_term": "Fil\u00e9 de Merluza"}, {"date": "08-06-2023", "aisle_name": "Frutos do mar", "product_name": "Fil\u00e9 de Merluza Sem Pele", "brand": "Pampa Fish", "price": 14.99, "package": "800g", "store_name": "Angeloni Supermercados", "store_city": "FLN", "search_term": "Fil\u00e9 de Merluza"}]